{
  "updated": "2026-07-02 15:37",
  "fx_gbp_usd": 1.3371,
  "stocks": [
    {
      "ticker": "BTC",
      "yf_ticker": "BTC-USD",
      "company_name": "Bitcoin",
      "category": "bitcoin",
      "exchange": "Crypto",
      "price_gbp": "46087",
      "price_usd": 61623.736865,
      "change_1d": "+3.17%",
      "change_1w": "+4.07%",
      "change_1m": "-9.14%",
      "change_ytd": "-29.59%",
      "return_1yr": "-30%",
      "low_gbp": "43789",
      "low_usd": 58550.747788,
      "high_gbp": "93316",
      "high_usd": 124773.508231,
      "bar_pct": 5,
      "market_cap_gbp_b": 924.1,
      "market_cap_usd_b": 1235.626,
      "avg_volume_m": 30645.05,
      "cmc_rank": 1,
      "beta": null,
      "pe_ratio": null,
      "div_yield_pct": null,
      "short_pct": null,
      "analyst": null,
      "analyst_score": null,
      "vol_1d": 38794170476,
      "vol_1w": 214515372818,
      "vol_1m": 1018073612194,
      "news": [
        {
          "title": "Bitcoin and ethereum prices today, Thursday, July 2: Prices move up following June jobs report",
          "publisher": "Yahoo Personal Finance",
          "url": "https://finance.yahoo.com/personal-finance/investing/article/bitcoin-and-ethereum-prices-today-thursday-july-2-prices-move-up-following-june-jobs-report-125118367.html",
          "published": 1782996678,
          "sentiment": 0.0
        },
        {
          "title": "Robinhood Jumps 6% on Bullish Analyst Initiations as Coinbase, Strategy Ride a Crypto-Stock Bounce",
          "publisher": "24/7 Wall St.",
          "url": "https://247wallst.com/investing/2026/07/02/robinhood-jumps-6-on-bullish-analyst-initiations-as-coinbase-strategy-ride-a-crypto-stock-bounce/",
          "published": 1783002585,
          "sentiment": 0.0
        },
        {
          "title": "Stock Market Today: Dow Climbs As Oil Dips Again; Tesla Slides But This Airline Outperforms (Live Coverage)",
          "publisher": "Investor's Business Daily",
          "url": "https://www.investors.com/market-trend/stock-market-today/dow-jones-sp500-nasdaq-jobs-report-tesla-deliveries-tsla-stock/?src=A00220&yptr=yahoo",
          "published": 1783001953,
          "sentiment": 0.0
        },
        {
          "title": "Robinhood, Strategy, Micron, Tesla, Palantir, Bending Spoons, and More Stocks That Explain Today\u2019s Market",
          "publisher": "Barrons.com",
          "url": "https://www.barrons.com/articles/stock-movers-4b343e08?siteid=yhoof2&yptr=yahoo",
          "published": 1783000980,
          "sentiment": 0.0
        },
        {
          "title": "Changpeng Zhao Forecasts Bitcoin\u2019s Price Will Reach $1 Million",
          "publisher": "CryptoProwl",
          "url": "https://www.cryptoprowl.com/releases/changpeng-zhao-forecasts-bitcoins-price-will-reach-1-million-6052",
          "published": 1783000380,
          "sentiment": 0.026
        }
      ],
      "news_sentiment": 0.005
    },
    {
      "ticker": "ETH",
      "yf_ticker": "ETH-USD",
      "company_name": "Ethereum",
      "category": "layer1",
      "exchange": "Crypto",
      "price_gbp": "1272",
      "price_usd": 1700.221811,
      "change_1d": "+5.99%",
      "change_1w": "+8.95%",
      "change_1m": "-12.12%",
      "change_ytd": "-42.69%",
      "return_1yr": "-43%",
      "low_gbp": "1170",
      "low_usd": 1564.842843,
      "high_gbp": "3612",
      "high_usd": 4829.225542,
      "bar_pct": 4,
      "market_cap_gbp_b": 153.456,
      "market_cap_usd_b": 205.188,
      "avg_volume_m": 10437.16,
      "cmc_rank": 2,
      "beta": null,
      "pe_ratio": null,
      "div_yield_pct": null,
      "short_pct": null,
      "analyst": null,
      "analyst_score": null,
      "vol_1d": 11297892394,
      "vol_1w": 73060117412,
      "vol_1m": 419287242105,
      "news": [
        {
          "title": "Bitcoin and ethereum prices today, Thursday, July 2: Prices move up following June jobs report",
          "publisher": "Yahoo Personal Finance",
          "url": "https://finance.yahoo.com/personal-finance/investing/article/bitcoin-and-ethereum-prices-today-thursday-july-2-prices-move-up-following-june-jobs-report-125118367.html",
          "published": 1782996678,
          "sentiment": 0.0
        },
        {
          "title": "Trump made $1B on crypto, his buyers got crushed",
          "publisher": "Yahoo Finance Video",
          "url": "https://finance.yahoo.com/video/trump-made-1b-on-crypto-his-buyers-got-crushed-155900664.html",
          "published": 1782921540,
          "sentiment": -0.421
        },
        {
          "title": "Morning Minute: Robinhood Debuts 'Robinhood Chain'",
          "publisher": "decrypt",
          "url": "https://decrypt.co/372667/morning-minute-robinhood-debuts-robinhood-chain",
          "published": 1782993986,
          "sentiment": 0.0
        },
        {
          "title": "HOOD Climbs 8% on Robinhood Chain Launch and an AI Guinness Record",
          "publisher": "BeInCrypto",
          "url": "https://beincrypto.com/robinhood-chain-mainnet-launch-guinness-record/",
          "published": 1782993839,
          "sentiment": 0.0
        },
        {
          "title": "1inch Integrates Robinhood Chain to Bring Tokenized Stocks and RWAs to 27M Users",
          "publisher": "CCN",
          "url": "https://www.ccn.com/news/crypto/1inch-robinhood-chain-tokenized-asset-trading/",
          "published": 1782991775,
          "sentiment": 0.0
        }
      ],
      "news_sentiment": -0.084
    },
    {
      "ticker": "SOL",
      "yf_ticker": "SOL-USD",
      "company_name": "Solana",
      "category": "layer1",
      "exchange": "Crypto",
      "price_gbp": "60",
      "price_usd": 80.509725,
      "change_1d": "+5.08%",
      "change_1w": "+22.62%",
      "change_1m": "+4.32%",
      "change_ytd": "-35.34%",
      "return_1yr": "-35%",
      "low_gbp": "46",
      "low_usd": 62.157877,
      "high_gbp": "185",
      "high_usd": 247.556262,
      "bar_pct": 10,
      "market_cap_gbp_b": 34.984,
      "market_cap_usd_b": 46.777,
      "avg_volume_m": 3137.37,
      "cmc_rank": 7,
      "beta": null,
      "pe_ratio": null,
      "div_yield_pct": null,
      "short_pct": null,
      "analyst": null,
      "analyst_score": null,
      "vol_1d": 3652959602,
      "vol_1w": 21961555435,
      "vol_1m": 92159701154,
      "news": [
        {
          "title": "Circle stock plummeted because of this new stablecoin. Here's why.",
          "publisher": "Yahoo Finance Video",
          "url": "https://finance.yahoo.com/video/circle-stock-plummeted-because-stablecoin-190000768.html",
          "published": 1782932400,
          "sentiment": 0.0
        },
        {
          "title": "Trump made $1B on crypto, his buyers got crushed",
          "publisher": "Yahoo Finance Video",
          "url": "https://finance.yahoo.com/video/trump-made-1b-on-crypto-his-buyers-got-crushed-155900664.html",
          "published": 1782921540,
          "sentiment": -0.421
        },
        {
          "title": "Which Crypto Is Best to Invest Now? XRP, Solana, Hyperliquid, or Chainlink?",
          "publisher": "24/7 Wall St.",
          "url": "https://247wallst.com/investing/cryptocurrency/2026/07/02/which-crypto-is-best-to-invest-now-xrp-solana-hyperliquid-or-chainlink/",
          "published": 1782996736,
          "sentiment": 0.677
        },
        {
          "title": "Crypto News Today (July 2): BTC Can\u2019t Reclaim $60K, Solana Sets Fresh Network Records, June Crypto Losses Top $76M",
          "publisher": "99bitcoins",
          "url": "https://99bitcoins.com/news/bitcoin-btc/crypto-news-today-july-2-btc-cant-reclaim-60k-solana-sets-fresh-network-records-june-crypto-losses-top-76m/",
          "published": 1782979820,
          "sentiment": 0.103
        },
        {
          "title": "Forward Industries Shares Rise 11% as Solana Bet Grows to 7.5 Million",
          "publisher": "BeInCrypto",
          "url": "https://beincrypto.com/forward-industries-solana-treasury-stock-rise/",
          "published": 1782971903,
          "sentiment": 0.296
        }
      ],
      "news_sentiment": 0.131
    },
    {
      "ticker": "BNB",
      "yf_ticker": "BNB-USD",
      "company_name": "BNB",
      "category": "layer1",
      "exchange": "Crypto",
      "price_gbp": "419",
      "price_usd": 560.752388,
      "change_1d": "+2.02%",
      "change_1w": "+1.62%",
      "change_1m": "-16.15%",
      "change_ytd": "-35.03%",
      "return_1yr": "-35%",
      "low_gbp": "408",
      "low_usd": 545.715777,
      "high_gbp": "981",
      "high_usd": 1311.712915,
      "bar_pct": 2,
      "market_cap_gbp_b": 56.525,
      "market_cap_usd_b": 75.58,
      "avg_volume_m": 737.65,
      "cmc_rank": 4,
      "beta": null,
      "pe_ratio": null,
      "div_yield_pct": null,
      "short_pct": null,
      "analyst": null,
      "analyst_score": null,
      "vol_1d": 824758698,
      "vol_1w": 5163534722,
      "vol_1m": 26648311692,
      "news": [
        {
          "title": "Top Cryptocurrencies Rise; Bitcoin Holds Above $60,000",
          "publisher": "MT Newswires",
          "url": "https://finance.yahoo.com/markets/crypto/articles/top-cryptocurrencies-rise-bitcoin-holds-195933659.html",
          "published": 1782935973,
          "sentiment": 0.202
        },
        {
          "title": "BNB Chain Pushes Self-Custody as MiCA Reshapes Europe's Crypto Market",
          "publisher": "CCN",
          "url": "https://www.ccn.com/news/crypto/bnb-chain-self-custody-mica-europe-crypto-market/",
          "published": 1782916035,
          "sentiment": 0.0
        },
        {
          "title": "1,700 Binance UK Customers Sue the Exchange for \u00a3150M",
          "publisher": "99bitcoins",
          "url": "https://99bitcoins.com/news/altcoins/binance-uk-lawsuit-crypto-derivatives/",
          "published": 1782899023,
          "sentiment": 0.0
        },
        {
          "title": "Hackers Steal $75.87 Million From Crypto Platforms in June 2026",
          "publisher": "BeInCrypto",
          "url": "https://beincrypto.com/crypto-hacks-june-2026-total-losses/",
          "published": 1782878839,
          "sentiment": -0.494
        },
        {
          "title": "Top Cryptocurrencies Fall; Bitcoin Drops Below $59,000 Level",
          "publisher": "MT Newswires",
          "url": "https://finance.yahoo.com/markets/crypto/articles/top-cryptocurrencies-fall-bitcoin-drops-195828743.html",
          "published": 1782849508,
          "sentiment": 0.202
        }
      ],
      "news_sentiment": -0.018
    },
    {
      "ticker": "ADA",
      "yf_ticker": "ADA-USD",
      "company_name": "Cardano",
      "category": "layer1",
      "exchange": "Crypto",
      "price_gbp": "0.1197",
      "price_usd": 0.160102,
      "change_1d": "+3.63%",
      "change_1w": "+12.24%",
      "change_1m": "-26.67%",
      "change_ytd": "-51.87%",
      "return_1yr": "-52%",
      "low_gbp": "0.1073",
      "low_usd": 0.143472,
      "high_gbp": "0.7204",
      "high_usd": 0.96321,
      "bar_pct": 2,
      "market_cap_gbp_b": 4.358,
      "market_cap_usd_b": 5.828,
      "avg_volume_m": 352.93,
      "cmc_rank": 15,
      "beta": null,
      "pe_ratio": null,
      "div_yield_pct": null,
      "short_pct": null,
      "analyst": null,
      "analyst_score": null,
      "vol_1d": 567461805,
      "vol_1w": 2470492587,
      "vol_1m": 14690499676,
      "news": [
        {
          "title": "Crypto News Today (July 2): BTC Can\u2019t Reclaim $60K, Solana Sets Fresh Network Records, June Crypto Losses Top $76M",
          "publisher": "99bitcoins",
          "url": "https://99bitcoins.com/news/bitcoin-btc/crypto-news-today-july-2-btc-cant-reclaim-60k-solana-sets-fresh-network-records-june-crypto-losses-top-76m/",
          "published": 1782979820,
          "sentiment": 0.103
        },
        {
          "title": "Top Cryptocurrencies Rise; Bitcoin Holds Above $60,000",
          "publisher": "MT Newswires",
          "url": "https://finance.yahoo.com/markets/crypto/articles/top-cryptocurrencies-rise-bitcoin-holds-195933659.html",
          "published": 1782935973,
          "sentiment": 0.202
        },
        {
          "title": "Should You Forget Altcoins and Just Buy Bitcoin Instead?",
          "publisher": "Motley Fool",
          "url": "https://www.fool.com/investing/2026/07/01/should-you-forget-altcoins-and-just-buy-bitcoin-in/",
          "published": 1782906600,
          "sentiment": -0.226
        },
        {
          "title": "Top Cryptocurrencies Fall; Bitcoin Drops Below $59,000 Level",
          "publisher": "MT Newswires",
          "url": "https://finance.yahoo.com/markets/crypto/articles/top-cryptocurrencies-fall-bitcoin-drops-195828743.html",
          "published": 1782849508,
          "sentiment": 0.202
        },
        {
          "title": "Webull Launches Crypto Trading In Canada",
          "publisher": "CryptoProwl",
          "url": "https://www.cryptoprowl.com/releases/webull-launches-crypto-trading-in-canada-6030",
          "published": 1782832020,
          "sentiment": 0.0
        }
      ],
      "news_sentiment": 0.056
    },
    {
      "ticker": "AVAX",
      "yf_ticker": "AVAX-USD",
      "company_name": "Avalanche",
      "category": "layer1",
      "exchange": "Crypto",
      "price_gbp": "5.05",
      "price_usd": 6.757089,
      "change_1d": "+1.17%",
      "change_1w": "+10.56%",
      "change_1m": "-19.92%",
      "change_ytd": "-45.10%",
      "return_1yr": "-45%",
      "low_gbp": "4.41",
      "low_usd": 5.890509,
      "high_gbp": "26",
      "high_usd": 35.281079,
      "bar_pct": 3,
      "market_cap_gbp_b": 2.182,
      "market_cap_usd_b": 2.918,
      "avg_volume_m": 217.93,
      "cmc_rank": 27,
      "beta": null,
      "pe_ratio": null,
      "div_yield_pct": null,
      "short_pct": null,
      "analyst": null,
      "analyst_score": null,
      "vol_1d": 201717120,
      "vol_1w": 1525492157,
      "vol_1m": 7190746746,
      "news": [
        {
          "title": "Should You Forget Altcoins and Just Buy Bitcoin Instead?",
          "publisher": "Motley Fool",
          "url": "https://www.fool.com/investing/2026/07/01/should-you-forget-altcoins-and-just-buy-bitcoin-in/",
          "published": 1782906600,
          "sentiment": -0.226
        }
      ],
      "news_sentiment": -0.226
    },
    {
      "ticker": "XRP",
      "yf_ticker": "XRP-USD",
      "company_name": "XRP",
      "category": "payments",
      "exchange": "Crypto",
      "price_gbp": "0.8161",
      "price_usd": 1.091247,
      "change_1d": "+3.58%",
      "change_1w": "+5.69%",
      "change_1m": "-11.45%",
      "change_ytd": "-40.67%",
      "return_1yr": "-41%",
      "low_gbp": "0.7768",
      "low_usd": 1.038645,
      "high_gbp": "2.66",
      "high_usd": 3.556293,
      "bar_pct": 2,
      "market_cap_gbp_b": 50.797,
      "market_cap_usd_b": 67.921,
      "avg_volume_m": 1688.59,
      "cmc_rank": 6,
      "beta": null,
      "pe_ratio": null,
      "div_yield_pct": null,
      "short_pct": null,
      "analyst": null,
      "analyst_score": null,
      "vol_1d": 1680559343,
      "vol_1w": 11820110717,
      "vol_1m": 58150732603,
      "news": [
        {
          "title": "Which Crypto Is Best to Invest Now? XRP, Solana, Hyperliquid, or Chainlink?",
          "publisher": "24/7 Wall St.",
          "url": "https://247wallst.com/investing/cryptocurrency/2026/07/02/which-crypto-is-best-to-invest-now-xrp-solana-hyperliquid-or-chainlink/",
          "published": 1782996736,
          "sentiment": 0.677
        },
        {
          "title": "Ripple Releases Monthly 1B XRP as Price Falls Over 70% \u2014 Is $2 Possible?",
          "publisher": "CCN",
          "url": "https://www.ccn.com/news/crypto/ripple-unlocks-1-billion-xrp-price-2-possible/",
          "published": 1782990435,
          "sentiment": 0.0
        },
        {
          "title": "Ripple, Coinbase Among Top Corporate Donors as Crypto Claims 37% of All 2026 Election Donations",
          "publisher": "Benzinga",
          "url": "https://finance.yahoo.com/markets/crypto/articles/ripple-coinbase-among-top-corporate-100103696.html",
          "published": 1782986463,
          "sentiment": 0.202
        },
        {
          "title": "Bitcoin, ETH, XRP Jump as Wall Street Sees Soft US Nonfarm Payrolls Data",
          "publisher": "CoinGape",
          "url": "https://coingape.com/bitcoin-eth-xrp-jump-as-wall-street-sees-soft-us-nonfarm-payrolls-data/",
          "published": 1782980452,
          "sentiment": 0.0
        },
        {
          "title": "Danger Builds for XRP as Holder Buying Sinks 11% Despite Price Rise",
          "publisher": "BeInCrypto",
          "url": "https://beincrypto.com/xrp-price-holder-buying-warning-analysis/",
          "published": 1782977481,
          "sentiment": -0.527
        }
      ],
      "news_sentiment": 0.07
    },
    {
      "ticker": "XLM",
      "yf_ticker": "XLM-USD",
      "company_name": "Stellar",
      "category": "payments",
      "exchange": "Crypto",
      "price_gbp": "0.1490",
      "price_usd": 0.199254,
      "change_1d": "-0.71%",
      "change_1w": "+12.30%",
      "change_1m": "-11.34%",
      "change_ytd": "-0.69%",
      "return_1yr": "-1%",
      "low_gbp": "0.1072",
      "low_usd": 0.143398,
      "high_gbp": "0.3762",
      "high_usd": 0.502966,
      "bar_pct": 16,
      "market_cap_gbp_b": 5.063,
      "market_cap_usd_b": 6.77,
      "avg_volume_m": 246.51,
      "cmc_rank": 13,
      "beta": null,
      "pe_ratio": null,
      "div_yield_pct": null,
      "short_pct": null,
      "analyst": null,
      "analyst_score": null,
      "vol_1d": 489543700,
      "vol_1w": 1725596462,
      "vol_1m": 12630660826,
      "news": [],
      "news_sentiment": null
    },
    {
      "ticker": "TRX",
      "yf_ticker": "TRX-USD",
      "company_name": "TRON",
      "category": "payments",
      "exchange": "Crypto",
      "price_gbp": "0.2380",
      "price_usd": 0.31823,
      "change_1d": "+0.25%",
      "change_1w": "-1.32%",
      "change_1m": "-5.52%",
      "change_ytd": "+11.91%",
      "return_1yr": "+12%",
      "low_gbp": "0.2014",
      "low_usd": 0.269328,
      "high_gbp": "0.2808",
      "high_usd": 0.375467,
      "bar_pct": 46,
      "market_cap_gbp_b": 22.574,
      "market_cap_usd_b": 30.185,
      "avg_volume_m": 513.44,
      "cmc_rank": 8,
      "beta": null,
      "pe_ratio": null,
      "div_yield_pct": null,
      "short_pct": null,
      "analyst": null,
      "analyst_score": null,
      "vol_1d": 458178577,
      "vol_1w": 3594087121,
      "vol_1m": 17049933390,
      "news": [],
      "news_sentiment": null
    },
    {
      "ticker": "SUI",
      "yf_ticker": "SUI20947-USD",
      "company_name": "Sui",
      "category": "emerging",
      "exchange": "Crypto",
      "price_gbp": "0.5535",
      "price_usd": 0.740066,
      "change_1d": "+4.18%",
      "change_1w": "+10.51%",
      "change_1m": "-10.66%",
      "change_ytd": "-47.23%",
      "return_1yr": "-47%",
      "low_gbp": "0.5091",
      "low_usd": 0.680783,
      "high_gbp": "3.24",
      "high_usd": 4.326642,
      "bar_pct": 2,
      "market_cap_gbp_b": 2.243,
      "market_cap_usd_b": 2.999,
      "avg_volume_m": 290.69,
      "cmc_rank": 26,
      "beta": null,
      "pe_ratio": null,
      "div_yield_pct": null,
      "short_pct": null,
      "analyst": null,
      "analyst_score": null,
      "vol_1d": 307374969,
      "vol_1w": 2034821614,
      "vol_1m": 12943432879,
      "news": [],
      "news_sentiment": null
    },
    {
      "ticker": "HBAR",
      "yf_ticker": "HBAR-USD",
      "company_name": "Hedera",
      "category": "emerging",
      "exchange": "Crypto",
      "price_gbp": "0.0555",
      "price_usd": 0.074235,
      "change_1d": "+5.35%",
      "change_1w": "+2.74%",
      "change_1m": "-16.86%",
      "change_ytd": "-30.09%",
      "return_1yr": "-30%",
      "low_gbp": "0.0519",
      "low_usd": 0.069379,
      "high_gbp": "0.2175",
      "high_usd": 0.290755,
      "bar_pct": 2,
      "market_cap_gbp_b": 2.423,
      "market_cap_usd_b": 3.24,
      "avg_volume_m": 57.92,
      "cmc_rank": 24,
      "beta": null,
      "pe_ratio": null,
      "div_yield_pct": null,
      "short_pct": null,
      "analyst": null,
      "analyst_score": null,
      "vol_1d": 63444702,
      "vol_1w": 405430405,
      "vol_1m": 2110938907,
      "news": [],
      "news_sentiment": null
    },
    {
      "ticker": "ALGO",
      "yf_ticker": "ALGO-USD",
      "company_name": "Algorand",
      "category": "emerging",
      "exchange": "Crypto",
      "price_gbp": "0.0648",
      "price_usd": 0.086636,
      "change_1d": "+2.05%",
      "change_1w": "+0.95%",
      "change_1m": "-25.73%",
      "change_ytd": "-21.37%",
      "return_1yr": "-21%",
      "low_gbp": "0.0606",
      "low_usd": 0.081023,
      "high_gbp": "0.2402",
      "high_usd": 0.321196,
      "bar_pct": 2,
      "market_cap_gbp_b": 0.58,
      "market_cap_usd_b": 0.775,
      "avg_volume_m": 30.07,
      "cmc_rank": 65,
      "beta": null,
      "pe_ratio": null,
      "div_yield_pct": null,
      "short_pct": null,
      "analyst": null,
      "analyst_score": null,
      "vol_1d": 28951171,
      "vol_1w": 210496262,
      "vol_1m": 1158934756,
      "news": [],
      "news_sentiment": null
    },
    {
      "ticker": "MINA",
      "yf_ticker": "MINA-USD",
      "company_name": "Mina",
      "category": "emerging",
      "exchange": "Crypto",
      "price_gbp": "0.0312",
      "price_usd": 0.041663,
      "change_1d": "+5.14%",
      "change_1w": "+9.21%",
      "change_1m": "-21.37%",
      "change_ytd": "-44.85%",
      "return_1yr": "-45%",
      "low_gbp": "0.0282",
      "low_usd": 0.037743,
      "high_gbp": "0.1779",
      "high_usd": 0.237877,
      "bar_pct": 2,
      "market_cap_gbp_b": 0.04,
      "market_cap_usd_b": 0.054,
      "avg_volume_m": 3.51,
      "cmc_rank": 369,
      "beta": null,
      "pe_ratio": null,
      "div_yield_pct": null,
      "short_pct": null,
      "analyst": null,
      "analyst_score": null,
      "vol_1d": 5496702,
      "vol_1w": 24549024,
      "vol_1m": 324911222,
      "news": [],
      "news_sentiment": null
    },
    {
      "ticker": "POL",
      "yf_ticker": "POL-USD",
      "company_name": "Polygon (MATIC)",
      "category": "infra",
      "exchange": "Crypto",
      "price_gbp": "0.0547",
      "price_usd": 0.073116,
      "change_1d": "+2.77%",
      "change_1w": "+4.72%",
      "change_1m": "-19.33%",
      "change_ytd": "-27.20%",
      "return_1yr": "-27%",
      "low_gbp": "0.0512",
      "low_usd": 0.068398,
      "high_gbp": "0.2164",
      "high_usd": 0.289392,
      "bar_pct": 2,
      "market_cap_gbp_b": 0.584,
      "market_cap_usd_b": 0.78,
      "avg_volume_m": 36.45,
      "cmc_rank": 64,
      "beta": null,
      "pe_ratio": null,
      "div_yield_pct": null,
      "short_pct": null,
      "analyst": null,
      "analyst_score": null,
      "vol_1d": 33662858,
      "vol_1w": 255128174,
      "vol_1m": 1330706931,
      "news": [],
      "news_sentiment": null
    },
    {
      "ticker": "DOT",
      "yf_ticker": "DOT-USD",
      "company_name": "Polkadot",
      "category": "infra",
      "exchange": "Crypto",
      "price_gbp": "0.6399",
      "price_usd": 0.855668,
      "change_1d": "+1.87%",
      "change_1w": "+1.52%",
      "change_1m": "-23.18%",
      "change_ytd": "-52.19%",
      "return_1yr": "-52%",
      "low_gbp": "0.6062",
      "low_usd": 0.810615,
      "high_gbp": "3.40",
      "high_usd": 4.541929,
      "bar_pct": 1,
      "market_cap_gbp_b": 1.082,
      "market_cap_usd_b": 1.447,
      "avg_volume_m": 84.27,
      "cmc_rank": 44,
      "beta": null,
      "pe_ratio": null,
      "div_yield_pct": null,
      "short_pct": null,
      "analyst": null,
      "analyst_score": null,
      "vol_1d": 83959988,
      "vol_1w": 589897933,
      "vol_1m": 3187336368,
      "news": [
        {
          "title": "Should You Forget Altcoins and Just Buy Bitcoin Instead?",
          "publisher": "Motley Fool",
          "url": "https://www.fool.com/investing/2026/07/01/should-you-forget-altcoins-and-just-buy-bitcoin-in/",
          "published": 1782906600,
          "sentiment": -0.226
        }
      ],
      "news_sentiment": -0.226
    },
    {
      "ticker": "LINK",
      "yf_ticker": "LINK-USD",
      "company_name": "Chainlink",
      "category": "infra",
      "exchange": "Crypto",
      "price_gbp": "5.87",
      "price_usd": 7.847542,
      "change_1d": "+6.69%",
      "change_1w": "+9.43%",
      "change_1m": "-9.19%",
      "change_ytd": "-35.64%",
      "return_1yr": "-36%",
      "low_gbp": "5.37",
      "low_usd": 7.183384,
      "high_gbp": "20",
      "high_usd": 26.746351,
      "bar_pct": 3,
      "market_cap_gbp_b": 4.267,
      "market_cap_usd_b": 5.706,
      "avg_volume_m": 206.76,
      "cmc_rank": 16,
      "beta": null,
      "pe_ratio": null,
      "div_yield_pct": null,
      "short_pct": null,
      "analyst": null,
      "analyst_score": null,
      "vol_1d": 211181251,
      "vol_1w": 1447313902,
      "vol_1m": 7948711881,
      "news": [
        {
          "title": "Which Crypto Is Best to Invest Now? XRP, Solana, Hyperliquid, or Chainlink?",
          "publisher": "24/7 Wall St.",
          "url": "https://247wallst.com/investing/cryptocurrency/2026/07/02/which-crypto-is-best-to-invest-now-xrp-solana-hyperliquid-or-chainlink/",
          "published": 1782996736,
          "sentiment": 0.677
        },
        {
          "title": "HOOD Climbs 8% on Robinhood Chain Launch and an AI Guinness Record",
          "publisher": "BeInCrypto",
          "url": "https://beincrypto.com/robinhood-chain-mainnet-launch-guinness-record/",
          "published": 1782993839,
          "sentiment": 0.0
        },
        {
          "title": "Robinhood Launches 'AI-Native' Ethereum Layer-2 Network, Tokenized Stock Trading",
          "publisher": "decrypt",
          "url": "https://decrypt.co/372614/robinhood-ai-native-ethereum-layer-2-network-tokenized-stock-trading",
          "published": 1782939398,
          "sentiment": 0.0
        },
        {
          "title": "Solana Prediction Market World Goes Live: Can It Take on Polymarket and Kalshi?",
          "publisher": "BeInCrypto",
          "url": "https://beincrypto.com/world-solana-prediction-market-phantom/",
          "published": 1782936673,
          "sentiment": 0.0
        },
        {
          "title": "3 Reasons Chainlink Could Skyrocket in 2026",
          "publisher": "Motley Fool",
          "url": "https://www.fool.com/investing/2026/06/29/3-reasons-chainlink-could-skyrocket-in-2026/",
          "published": 1782740160,
          "sentiment": 0.0
        }
      ],
      "news_sentiment": 0.135
    },
    {
      "ticker": "DOGE",
      "yf_ticker": "DOGE-USD",
      "company_name": "Dogecoin",
      "category": "meme",
      "exchange": "Crypto",
      "price_gbp": "0.0558",
      "price_usd": 0.074617,
      "change_1d": "+2.91%",
      "change_1w": "+1.95%",
      "change_1m": "-22.06%",
      "change_ytd": "-36.38%",
      "return_1yr": "-36%",
      "low_gbp": "0.0538",
      "low_usd": 0.071972,
      "high_gbp": "0.2164",
      "high_usd": 0.289384,
      "bar_pct": 1,
      "market_cap_gbp_b": 8.644,
      "market_cap_usd_b": 11.558,
      "avg_volume_m": 620.85,
      "cmc_rank": 10,
      "beta": null,
      "pe_ratio": null,
      "div_yield_pct": null,
      "short_pct": null,
      "analyst": null,
      "analyst_score": null,
      "vol_1d": 613124594,
      "vol_1w": 4345983858,
      "vol_1m": 23318238775,
      "news": [
        {
          "title": "Bitcoin Spikes as Kevin Warsh Flags Inflation Concerns; Ethereum, XRP, Dogecoin Also Gain: Popular Analyst Says 'Market Bottom Is Here'",
          "publisher": "Benzinga",
          "url": "https://finance.yahoo.com/markets/crypto/articles/bitcoin-spikes-kevin-warsh-flags-015910365.html",
          "published": 1782957550,
          "sentiment": 0.735
        },
        {
          "title": "Top Cryptocurrencies Rise; Bitcoin Holds Above $60,000",
          "publisher": "MT Newswires",
          "url": "https://finance.yahoo.com/markets/crypto/articles/top-cryptocurrencies-rise-bitcoin-holds-195933659.html",
          "published": 1782935973,
          "sentiment": 0.202
        },
        {
          "title": "Here's What History Says Comes Next For Dogecoin in July",
          "publisher": "Motley Fool",
          "url": "https://www.fool.com/investing/2026/07/01/heres-what-history-says-comes-next-for-dogecoin-in/",
          "published": 1782906900,
          "sentiment": 0.0
        },
        {
          "title": "Bitcoin, Ethereum, XRP, Dogecoin Slide as 'Extreme Fear' Persists: Analyst Notes Half of BTC Circulating Network Now Sitting 'Underwater'",
          "publisher": "Benzinga",
          "url": "https://finance.yahoo.com/markets/crypto/articles/bitcoin-ethereum-xrp-dogecoin-slide-014634065.html",
          "published": 1782870394,
          "sentiment": -0.541
        },
        {
          "title": "Director sentenced for using Netflix funds to trade crypto",
          "publisher": "Yahoo Finance Video",
          "url": "https://finance.yahoo.com/video/director-sentenced-using-netflix-funds-203000772.html",
          "published": 1782851400,
          "sentiment": -0.026
        }
      ],
      "news_sentiment": 0.074
    },
    {
      "ticker": "PEPE",
      "yf_ticker": "PEPE24478-USD",
      "company_name": "Pepe",
      "category": "meme",
      "exchange": "Crypto",
      "price_gbp": "0.00000183",
      "price_usd": 2e-06,
      "change_1d": "+6.13%",
      "change_1w": "+2.96%",
      "change_1m": "-24.40%",
      "change_ytd": "-39.44%",
      "return_1yr": "-39%",
      "low_gbp": "0.00000174",
      "low_usd": 2e-06,
      "high_gbp": "0.00001061",
      "high_usd": 1.4e-05,
      "bar_pct": 1,
      "market_cap_gbp_b": 0.756,
      "market_cap_usd_b": 1.011,
      "avg_volume_m": 143.11,
      "cmc_rank": 55,
      "beta": null,
      "pe_ratio": null,
      "div_yield_pct": null,
      "short_pct": null,
      "analyst": null,
      "analyst_score": null,
      "vol_1d": 186500520,
      "vol_1w": 1001740621,
      "vol_1m": 5370648547,
      "news": [
        {
          "title": "Pavel Durov Gifts $12,000 Worth of Plush Pepe NFT to a Telegram Designer",
          "publisher": "BeInCrypto",
          "url": "https://beincrypto.com/pavel-durov-plush-pepe-nft-gram-ton/",
          "published": 1782562857,
          "sentiment": 0.226
        }
      ],
      "news_sentiment": 0.226
    },
    {
      "ticker": "TAO",
      "yf_ticker": "TAO-USD",
      "company_name": "Bittensor",
      "category": "ai",
      "exchange": "Crypto",
      "price_gbp": "161",
      "price_usd": 215.41225,
      "change_1d": "+6.67%",
      "change_1w": "+1.74%",
      "change_1m": "-10.91%",
      "change_ytd": "-1.49%",
      "return_1yr": "-1%",
      "low_gbp": "109",
      "low_usd": 145.650057,
      "high_gbp": "373",
      "high_usd": 498.180074,
      "bar_pct": 20,
      "market_cap_gbp_b": 1.785,
      "market_cap_usd_b": 2.387,
      "avg_volume_m": 134.14,
      "cmc_rank": 33,
      "beta": null,
      "pe_ratio": null,
      "div_yield_pct": null,
      "short_pct": null,
      "analyst": null,
      "analyst_score": null,
      "vol_1d": 153829221,
      "vol_1w": 938976679,
      "vol_1m": 7393907795,
      "news": [],
      "news_sentiment": null
    },
    {
      "ticker": "FET",
      "yf_ticker": "FET-USD",
      "company_name": "ASI Alliance",
      "category": "ai",
      "exchange": "Crypto",
      "price_gbp": "0.1366",
      "price_usd": 0.182691,
      "change_1d": "+1.88%",
      "change_1w": "+10.36%",
      "change_1m": "-31.33%",
      "change_ytd": "-8.06%",
      "return_1yr": "-8%",
      "low_gbp": "0.1056",
      "low_usd": 0.141246,
      "high_gbp": "0.6300",
      "high_usd": 0.84237,
      "bar_pct": 6,
      "market_cap_gbp_b": 0.307,
      "market_cap_usd_b": 0.411,
      "avg_volume_m": 54.76,
      "cmc_rank": 86,
      "beta": null,
      "pe_ratio": null,
      "div_yield_pct": null,
      "short_pct": null,
      "analyst": null,
      "analyst_score": null,
      "vol_1d": 63937482,
      "vol_1w": 383344333,
      "vol_1m": 2674952943,
      "news": [],
      "news_sentiment": null
    },
    {
      "ticker": "RNDR",
      "yf_ticker": "RNDR-USD",
      "company_name": "Render",
      "category": "ai",
      "exchange": "Crypto",
      "price_gbp": "1.19",
      "price_usd": 1.587079,
      "change_1d": "+3.23%",
      "change_1w": "+5.61%",
      "change_1m": "-25.36%",
      "change_ytd": "+23.59%",
      "return_1yr": "+24%",
      "low_gbp": "0.9046",
      "low_usd": 1.209599,
      "high_gbp": "3.43",
      "high_usd": 4.588173,
      "bar_pct": 11,
      "market_cap_gbp_b": 0.616,
      "market_cap_usd_b": 0.823,
      "avg_volume_m": 40.93,
      "cmc_rank": 60,
      "beta": null,
      "pe_ratio": null,
      "div_yield_pct": null,
      "short_pct": null,
      "analyst": null,
      "analyst_score": null,
      "vol_1d": 42253456,
      "vol_1w": 286528549,
      "vol_1m": 2005464470,
      "news": [],
      "news_sentiment": null
    },
    {
      "ticker": "OCEAN",
      "yf_ticker": "OCEAN-USD",
      "company_name": "Ocean Protocol",
      "category": "ai",
      "exchange": "Crypto",
      "price_gbp": "0.0857",
      "price_usd": 0.114528,
      "change_1d": "+0.94%",
      "change_1w": "+29.74%",
      "change_1m": "-13.16%",
      "change_ytd": "-23.94%",
      "return_1yr": "-24%",
      "low_gbp": "0.0651",
      "low_usd": 0.08704,
      "high_gbp": "0.2755",
      "high_usd": 0.368427,
      "bar_pct": 10,
      "market_cap_gbp_b": null,
      "market_cap_usd_b": null,
      "avg_volume_m": 0.29,
      "cmc_rank": 4361,
      "beta": null,
      "pe_ratio": null,
      "div_yield_pct": null,
      "short_pct": null,
      "analyst": null,
      "analyst_score": null,
      "vol_1d": 33935,
      "vol_1w": 2006588,
      "vol_1m": 3446602,
      "news": [],
      "news_sentiment": null
    },
    {
      "ticker": "GRT",
      "yf_ticker": "GRT-USD",
      "company_name": "The Graph",
      "category": "ai",
      "exchange": "Crypto",
      "price_gbp": "0.0136",
      "price_usd": 0.018226,
      "change_1d": "+2.63%",
      "change_1w": "+3.50%",
      "change_1m": "-23.82%",
      "change_ytd": "-45.18%",
      "return_1yr": "-45%",
      "low_gbp": "0.0132",
      "low_usd": 0.017595,
      "high_gbp": "0.0868",
      "high_usd": 0.116064,
      "bar_pct": 1,
      "market_cap_gbp_b": 0.148,
      "market_cap_usd_b": 0.198,
      "avg_volume_m": 15.55,
      "cmc_rank": 126,
      "beta": null,
      "pe_ratio": null,
      "div_yield_pct": null,
      "short_pct": null,
      "analyst": null,
      "analyst_score": null,
      "vol_1d": 16089835,
      "vol_1w": 108818123,
      "vol_1m": 453864536,
      "news": [],
      "news_sentiment": null
    },
    {
      "ticker": "AGIX",
      "yf_ticker": "AGIX-USD",
      "company_name": "SingularityNET",
      "category": "ai",
      "exchange": "Crypto",
      "price_gbp": "0.0590",
      "price_usd": 0.078871,
      "change_1d": "+1.14%",
      "change_1w": "+9.46%",
      "change_1m": "-33.36%",
      "change_ytd": "-8.02%",
      "return_1yr": "-8%",
      "low_gbp": "0.0133",
      "low_usd": 0.017819,
      "high_gbp": "0.2732",
      "high_usd": 0.365305,
      "bar_pct": 18,
      "market_cap_gbp_b": null,
      "market_cap_usd_b": null,
      "avg_volume_m": 0.01,
      "cmc_rank": 4773,
      "beta": null,
      "pe_ratio": null,
      "div_yield_pct": null,
      "short_pct": null,
      "analyst": null,
      "analyst_score": null,
      "vol_1d": 12479,
      "vol_1w": 73057,
      "vol_1m": 500649,
      "news": [],
      "news_sentiment": null
    },
    {
      "ticker": "NMR",
      "yf_ticker": "NMR-USD",
      "company_name": "Numeraire",
      "category": "ai",
      "exchange": "Crypto",
      "price_gbp": "7.03",
      "price_usd": 9.400882,
      "change_1d": "+0.52%",
      "change_1w": "+10.56%",
      "change_1m": "+10.72%",
      "change_ytd": "-1.61%",
      "return_1yr": "-2%",
      "low_gbp": "4.72",
      "low_usd": 6.305606,
      "high_gbp": "16",
      "high_usd": 20.785081,
      "bar_pct": 21,
      "market_cap_gbp_b": 0.053,
      "market_cap_usd_b": 0.07,
      "avg_volume_m": 6.46,
      "cmc_rank": 301,
      "beta": null,
      "pe_ratio": null,
      "div_yield_pct": null,
      "short_pct": null,
      "analyst": null,
      "analyst_score": null,
      "vol_1d": 8124358,
      "vol_1w": 45231048,
      "vol_1m": 190327440,
      "news": [],
      "news_sentiment": null
    },
    {
      "ticker": "ALT",
      "yf_ticker": "ALT-USD",
      "company_name": "AltLayer",
      "category": "ai",
      "exchange": "Crypto",
      "price_gbp": "0.00448363",
      "price_usd": 0.005995,
      "change_1d": "+3.60%",
      "change_1w": "+7.73%",
      "change_1m": "-11.13%",
      "change_ytd": "-47.64%",
      "return_1yr": "-48%",
      "low_gbp": "0.00420115",
      "low_usd": 0.005617,
      "high_gbp": "0.0308",
      "high_usd": 0.041208,
      "bar_pct": 1,
      "market_cap_gbp_b": 0.03,
      "market_cap_usd_b": 0.04,
      "avg_volume_m": 3.53,
      "cmc_rank": 462,
      "beta": null,
      "pe_ratio": null,
      "div_yield_pct": null,
      "short_pct": null,
      "analyst": null,
      "analyst_score": null,
      "vol_1d": 3838595,
      "vol_1w": 24732869,
      "vol_1m": 240061581,
      "news": [],
      "news_sentiment": null
    },
    {
      "ticker": "AIOZ",
      "yf_ticker": "AIOZ-USD",
      "company_name": "AIOZ Network",
      "category": "ai",
      "exchange": "Crypto",
      "price_gbp": "0.0403",
      "price_usd": 0.053938,
      "change_1d": "+2.84%",
      "change_1w": "+3.65%",
      "change_1m": "-14.10%",
      "change_ytd": "-37.75%",
      "return_1yr": "-38%",
      "low_gbp": "0.0388",
      "low_usd": 0.051912,
      "high_gbp": "0.3491",
      "high_usd": 0.466806,
      "bar_pct": 1,
      "market_cap_gbp_b": 0.051,
      "market_cap_usd_b": 0.068,
      "avg_volume_m": 3.63,
      "cmc_rank": 306,
      "beta": null,
      "pe_ratio": null,
      "div_yield_pct": null,
      "short_pct": null,
      "analyst": null,
      "analyst_score": null,
      "vol_1d": 3271274,
      "vol_1w": 25404601,
      "vol_1m": 127855046,
      "news": [],
      "news_sentiment": null
    },
    {
      "ticker": "ARKM",
      "yf_ticker": "ARKM-USD",
      "company_name": "Arkham",
      "category": "ai",
      "exchange": "Crypto",
      "price_gbp": "0.0855",
      "price_usd": 0.114299,
      "change_1d": "+2.31%",
      "change_1w": "-1.10%",
      "change_1m": "-18.25%",
      "change_ytd": "-35.22%",
      "return_1yr": "-35%",
      "low_gbp": "0.0705",
      "low_usd": 0.09432,
      "high_gbp": "0.4973",
      "high_usd": 0.664888,
      "bar_pct": 4,
      "market_cap_gbp_b": 0.019,
      "market_cap_usd_b": 0.026,
      "avg_volume_m": 5.91,
      "cmc_rank": 622,
      "beta": null,
      "pe_ratio": null,
      "div_yield_pct": null,
      "short_pct": null,
      "analyst": null,
      "analyst_score": null,
      "vol_1d": 6232295,
      "vol_1w": 41360356,
      "vol_1m": 326000508,
      "news": [],
      "news_sentiment": null
    },
    {
      "ticker": "WLD",
      "yf_ticker": "WLD-USD",
      "company_name": "Worldcoin",
      "category": "ai",
      "exchange": "Crypto",
      "price_gbp": "0.2923",
      "price_usd": 0.390823,
      "change_1d": "-1.37%",
      "change_1w": "-21.18%",
      "change_1m": "-6.40%",
      "change_ytd": "-18.75%",
      "return_1yr": "-19%",
      "low_gbp": "0.1749",
      "low_usd": 0.233905,
      "high_gbp": "1.45",
      "high_usd": 1.939647,
      "bar_pct": 9,
      "market_cap_gbp_b": 1.025,
      "market_cap_usd_b": 1.371,
      "avg_volume_m": 227.34,
      "cmc_rank": 46,
      "beta": null,
      "pe_ratio": null,
      "div_yield_pct": null,
      "short_pct": null,
      "analyst": null,
      "analyst_score": null,
      "vol_1d": 304541650,
      "vol_1w": 1591390800,
      "vol_1m": 19352709858,
      "news": [],
      "news_sentiment": null
    },
    {
      "ticker": "NEAR",
      "yf_ticker": "NEAR-USD",
      "company_name": "NEAR Protocol",
      "category": "ai",
      "exchange": "Crypto",
      "price_gbp": "1.43",
      "price_usd": 1.917891,
      "change_1d": "+5.39%",
      "change_1w": "+3.47%",
      "change_1m": "-26.54%",
      "change_ytd": "+26.81%",
      "return_1yr": "+27%",
      "low_gbp": "0.7184",
      "low_usd": 0.960521,
      "high_gbp": "2.39",
      "high_usd": 3.196852,
      "bar_pct": 43,
      "market_cap_gbp_b": 1.864,
      "market_cap_usd_b": 2.493,
      "avg_volume_m": 262.58,
      "cmc_rank": 32,
      "beta": null,
      "pe_ratio": null,
      "div_yield_pct": null,
      "short_pct": null,
      "analyst": null,
      "analyst_score": null,
      "vol_1d": 261517422,
      "vol_1w": 1838051645,
      "vol_1m": 14214598844,
      "news": [],
      "news_sentiment": null
    },
    {
      "ticker": "ICP",
      "yf_ticker": "ICP-USD",
      "company_name": "Internet Computer",
      "category": "ai",
      "exchange": "Crypto",
      "price_gbp": "1.66",
      "price_usd": 2.219903,
      "change_1d": "+2.17%",
      "change_1w": "+3.67%",
      "change_1m": "-26.90%",
      "change_ytd": "-21.70%",
      "return_1yr": "-22%",
      "low_gbp": "1.56",
      "low_usd": 2.084533,
      "high_gbp": "6.72",
      "high_usd": 8.982771,
      "bar_pct": 2,
      "market_cap_gbp_b": 0.92,
      "market_cap_usd_b": 1.23,
      "avg_volume_m": 38.3,
      "cmc_rank": 50,
      "beta": null,
      "pe_ratio": null,
      "div_yield_pct": null,
      "short_pct": null,
      "analyst": null,
      "analyst_score": null,
      "vol_1d": 45416990,
      "vol_1w": 268094742,
      "vol_1m": 2029312838,
      "news": [],
      "news_sentiment": null
    },
    {
      "ticker": "KAITO",
      "yf_ticker": "KAITO-USD",
      "company_name": "Kaito",
      "category": "ai",
      "exchange": "Crypto",
      "price_gbp": "0.4267",
      "price_usd": 0.570604,
      "change_1d": "-2.35%",
      "change_1w": "+25.13%",
      "change_1m": "+29.04%",
      "change_ytd": "+12.72%",
      "return_1yr": "+13%",
      "low_gbp": "0.2177",
      "low_usd": 0.291124,
      "high_gbp": "1.30",
      "high_usd": 1.742911,
      "bar_pct": 19,
      "market_cap_gbp_b": 0.103,
      "market_cap_usd_b": 0.138,
      "avg_volume_m": 19.51,
      "cmc_rank": 149,
      "beta": null,
      "pe_ratio": null,
      "div_yield_pct": null,
      "short_pct": null,
      "analyst": null,
      "analyst_score": null,
      "vol_1d": 18280912,
      "vol_1w": 136560927,
      "vol_1m": 465931643,
      "news": [],
      "news_sentiment": null
    },
    {
      "ticker": "VIRTUAL",
      "yf_ticker": "VIRTUAL-USD",
      "company_name": "Virtuals Protocol",
      "category": "ai",
      "exchange": "Crypto",
      "price_gbp": "0.4177",
      "price_usd": 0.558466,
      "change_1d": "+1.72%",
      "change_1w": "+7.97%",
      "change_1m": "-22.48%",
      "change_ytd": "-13.60%",
      "return_1yr": "-14%",
      "low_gbp": "0.3879",
      "low_usd": 0.518646,
      "high_gbp": "1.44",
      "high_usd": 1.927115,
      "bar_pct": 3,
      "market_cap_gbp_b": 0.275,
      "market_cap_usd_b": 0.367,
      "avg_volume_m": 43.96,
      "cmc_rank": 92,
      "beta": null,
      "pe_ratio": null,
      "div_yield_pct": null,
      "short_pct": null,
      "analyst": null,
      "analyst_score": null,
      "vol_1d": 51639751,
      "vol_1w": 307740704,
      "vol_1m": 2074806482,
      "news": [
        {
          "title": "AI Agents Expand Into Tokenized Stocks as Agentic Finance Race Accelerates",
          "publisher": "BeInCrypto",
          "url": "https://beincrypto.com/ai-agents-ondo-tokenized-stocks-virtuals/",
          "published": 1782467810,
          "sentiment": 0.318
        }
      ],
      "news_sentiment": 0.318
    }
  ]
}